pg_cnab240/__init__.py
pg_cnab240/attribute.py
pg_cnab240/company.py
pg_cnab240/file.py
pg_cnab240/file_section.py
pg_cnab240/payment.py
pg_cnab240/segment_section.py
pg_cnab240/banks/__init__.py
pg_cnab240/banks/bank.py
pg_cnab240/banks/bank_account.py
pg_cnab240/banks/itau/__init__.py
pg_cnab240/banks/itau/file_footer.py
pg_cnab240/banks/itau/file_header.py
pg_cnab240/banks/itau/itau.py
pg_cnab240/banks/itau/segments/A.py
pg_cnab240/banks/itau/segments/J.py
pg_cnab240/banks/itau/segments/__init__.py
pg_cnab240/banks/itau/segments/footers/__init__.py
pg_cnab240/banks/itau/segments/footers/slip_footer.py
pg_cnab240/banks/itau/segments/footers/transfer_footer.py
pg_cnab240/banks/itau/segments/headers/__init__.py
pg_cnab240/banks/itau/segments/headers/slip_header.py
pg_cnab240/banks/itau/segments/headers/transfer_header.py
pg_cnab240-1.0.5.dist-info/METADATA
pg_cnab240-1.0.5.dist-info/RECORD
pg_cnab240-1.0.5.dist-info/WHEEL
pg_cnab240-1.0.5.dist-info/top_level.txt
tests/ItauFileTestCase.py
tests/__init__.py
