Metadata-Version: 2.1
Name: pg-cnab240
Version: 1.0.5
Summary: A CNAB 240 Package to process Bank payment shipping files and return files.
Home-page: https://github.com/BancoDeFormaturas/python-pg-cnab240
Author: Banco de Formaturas
Author-email: alamo.saravali@bancodeformaturas.com.br
License: UNKNOWN
Platform: UNKNOWN
Classifier: Programming Language :: Python :: 3
Classifier: License :: OSI Approved :: MIT License
Classifier: Operating System :: OS Independent
